wattrex_driver_pwr/__init__.py
wattrex_driver_pwr/__version__.py
wattrex_driver_pwr/drv_pwr.py
wattrex_driver_pwr-0.0.1.dist-info/LICENSE.txt
wattrex_driver_pwr-0.0.1.dist-info/METADATA
wattrex_driver_pwr-0.0.1.dist-info/WHEEL
wattrex_driver_pwr-0.0.1.dist-info/top_level.txt
wattrex_driver_pwr-0.0.1.dist-info/RECORD
